valyu_agentcore/__init__.py
valyu_agentcore/gateway.py
valyu_agentcore/py.typed
valyu_agentcore/tools.py
valyu_agentcore/version.py
valyu_agentcore-0.1.3.dist-info/METADATA
valyu_agentcore-0.1.3.dist-info/WHEEL
valyu_agentcore-0.1.3.dist-info/licenses/LICENSE
valyu_agentcore-0.1.3.dist-info/RECORD
