Metadata-Version: 2.4
Name: valyu-agentcore
Version: 0.1.3
Summary: Valyu search tools for AWS Bedrock AgentCore - web, finance, academic, biomedical, patent, SEC, and economics search
Project-URL: Homepage, https://valyu.ai
Project-URL: Documentation, https://docs.valyu.ai
Project-URL: Repository, https://github.com/valyu-network/valyu-agentcore
Project-URL: Changelog, https://github.com/valyu-network/valyu-agentcore/releases
Project-URL: API Key, https://platform.valyu.ai
Author-email: Valyu <contact@valyu.ai>
License-Expression: MIT
License-File: LICENSE
Keywords: academic-papers,agentcore,ai-agents,aws,bedrock,financial-data,mcp,rag,research,search,sec-filings,strands,valyu,web-search
Classifier: Development Status :: 4 - Beta
Classifier: Intended Audience :: Developers
Classifier: License :: OSI Approved :: MIT License
Classifier: Programming Language :: Python :: 3
Classifier: Programming Language :: Python :: 3.10
Classifier: Programming Language :: Python :: 3.11
Classifier: Programming Language :: Python :: 3.12
Classifier: Topic :: Internet :: WWW/HTTP :: Indexing/Search
Classifier: Topic :: Scientific/Engineering :: Artificial Intelligence
Requires-Python: >=3.10
Requires-Dist: httpx>=0.24.0
Provides-Extra: agentcore
Requires-Dist: bedrock-agentcore-starter-toolkit>=0.2.0; extra == 'agentcore'
Requires-Dist: bedrock-agentcore>=1.0.0; extra == 'agentcore'
Requires-Dist: boto3>=1.42.0; extra == 'agentcore'
Requires-Dist: mcp>=1.0.0; extra == 'agentcore'
Requires-Dist: strands-agents>=0.1.0; extra == 'agentcore'
Provides-Extra: all
Requires-Dist: bedrock-agentcore-starter-toolkit>=0.2.0; extra == 'all'
Requires-Dist: bedrock-agentcore>=1.0.0; extra == 'all'
Requires-Dist: boto3>=1.42.0; extra == 'all'
Requires-Dist: langchain-core>=0.1.0; extra == 'all'
Requires-Dist: mcp>=1.0.0; extra == 'all'
Requires-Dist: strands-agents>=0.1.0; extra == 'all'
Provides-Extra: demo
Requires-Dist: boto3>=1.28.0; extra == 'demo'
Requires-Dist: pyyaml>=6.0.0; extra == 'demo'
Requires-Dist: strands-agents>=0.1.0; extra == 'demo'
Requires-Dist: streamlit>=1.30.0; extra == 'demo'
Provides-Extra: dev
Requires-Dist: mypy>=1.0.0; extra == 'dev'
Requires-Dist: pytest-asyncio>=0.21.0; extra == 'dev'
Requires-Dist: pytest>=7.0.0; extra == 'dev'
Requires-Dist: respx>=0.20.0; extra == 'dev'
Requires-Dist: ruff>=0.1.0; extra == 'dev'
Provides-Extra: langchain
Requires-Dist: langchain-core>=0.1.0; extra == 'langchain'
Provides-Extra: strands
Requires-Dist: boto3>=1.28.0; extra == 'strands'
Requires-Dist: strands-agents>=0.1.0; extra == 'strands'
